oneNeuron/__init__.py
oneNeuron/perceptron.py
oneNeuron_pkg_Vikaslakkacs-0.0.5.dist-info/LICENSE
oneNeuron_pkg_Vikaslakkacs-0.0.5.dist-info/METADATA
oneNeuron_pkg_Vikaslakkacs-0.0.5.dist-info/WHEEL
oneNeuron_pkg_Vikaslakkacs-0.0.5.dist-info/top_level.txt
oneNeuron_pkg_Vikaslakkacs-0.0.5.dist-info/RECORD
