Metadata-Version: 2.1
Name: oneNeuron-pkg-Vikaslakkacs
Version: 0.0.5
Summary: A small for perceptron
Home-page: https://github.com/Vikaslakkacs/Python_package_creation
Author: Example Author
Author-email: vikaslakkacs@gmail.com
Project-URL: Bug Tracker, https://github.com/Vikaslakkacs/Python_package_creation/issues
Classifier: Programming Language :: Python :: 3
Classifier: License :: OSI Approved :: MIT License
Classifier: Operating System :: OS Independent
Requires-Python: >=3.6
License-File: LICENSE
Requires-Dist: numpy (==1.21.6)
Requires-Dist: pandas (==1.3.5)
Requires-Dist: joblib (==1.1.0)
